{"cameraMode":{"drawMode":0,"name":"Shaded","section":"Shading Mode"},"sceneLighting":false,"audioPlay":false,"sceneViewState":{"m_AlwaysRefresh":false,"showFog":true,"showSkybox":false,"showFlares":true,"showImageEffects":true,"showParticleSystems":true,"showVisualEffectGraphs":true,"m_FxEnabled":true},"in2DMode":false,"pivot":{"x":1.0,"y":-0.08999991416931153,"z":0.75},"rotation":{"x":0.28931349515914919,"y":-0.054524704813957217,"z":0.0165094044059515,"w":0.95554119348526},"size":10.0,"orthographic":false}